ifcdiff.py
ifcdiff-0.8.3.dist-info/METADATA
ifcdiff-0.8.3.dist-info/WHEEL
ifcdiff-0.8.3.dist-info/top_level.txt
ifcdiff-0.8.3.dist-info/RECORD
